toolbox/__init__.py
toolbox/asciify.py
toolbox/converters.py
toolbox/db.py
toolbox/flatten.py
toolbox/log.py
toolbox/object.py
toolbox/silent.py
toolbox/similarity.py
toolbox/store.py
toolbox/timer.py
toolbox_py-0.0.1.dist-info/LICENSE
toolbox_py-0.0.1.dist-info/METADATA
toolbox_py-0.0.1.dist-info/WHEEL
toolbox_py-0.0.1.dist-info/top_level.txt
toolbox_py-0.0.1.dist-info/RECORD
